setup.mongo.py
setup.py
ma.egg-info/PKG-INFO
ma.egg-info/SOURCES.txt
ma.egg-info/dependency_links.txt
ma.egg-info/requires.txt
ma.egg-info/top_level.txt
ma/mongo/__init__.py
ma/mongo/lock.py
ma/mongo/log.py
ma/mongo/validate.py