Metadata-Version: 1.0
Name: ma
Version: 1.0.0
Summary: Collection of tools and utilities. This is just a metapackage,
Home-page: UNKNOWN
Author: Fredrik Haard
Author-email: fredrik@metallapan.se
License: UNKNOWN
Platform: UNKNOWN
